{
  "loras": [
    {
      "name": "SDXL Offset Example",
      "description": "Official SDXL offset LoRA for sharper detail (Stability AI).",
      "repo_id": "stabilityai/sd_xl_offset_example-lora_1.0",
      "filename": "sd_xl_offset_example-lora_1.0.safetensors",
      "path": "stabilityai/stable-diffusion-xl-base-1.0/sd_xl_offset_example-lora_1.0.safetensors",
      "preview_url": "https://huggingface.co/stabilityai/sd_xl_offset_example-lora_1.0/resolve/main/An_example_image.png",
      "tags": ["sdxl", "detail", "general"]
    },
    {
      "name": "Pixel Art Character XL",
      "description": "Public SDXL pixel-art LoRA (nerijs).",
      "repo_id": "nerijs/pixel-art-xl",
      "filename": "pixel-art-xl.safetensors",
      "path": "lora/pixel-art-xl.safetensors",
      "tags": ["sdxl", "pixel art", "character"]
    },
    {
      "name": "Shaded Retro Anime SDXL",
      "description": "Stylised anime shading LoRA by nDimensional.",
      "repo_id": "nDimensional/Shaded-Retro-Style-Anime-with-Natural-Language-SDXL-LoRA",
      "filename": "Shaded-Retro-Anime-000006.safetensors",
      "path": "lora/Shaded-Retro-Anime-000006.safetensors",
      "tags": ["sdxl", "anime", "character"]
    },
    {
      "name": "Mini Mecha SDXL",
      "description": "Mecha-focused SDXL LoRA by Yangdf.",
      "repo_id": "Yangdf/mini-mecha-sdxl-lora",
      "filename": "mini-mecha-sdxl-lora.safetensors",
      "path": "lora/mini-mecha-sdxl-lora.safetensors",
      "tags": ["sdxl", "mecha", "character"]
    },
    {
      "name": "Anime Companion SDXL",
      "description": "Stylised anime companion character LoRA for SDXL.",
      "repo_id": "Meina/AnimeCharacterSDXL-LoRA",
      "filename": "anime-companion.safetensors",
      "path": "lora/anime-companion.safetensors",
      "preview_url": "https://huggingface.co/Meina/AnimeCharacterSDXL-LoRA/resolve/main/preview.png",
      "tags": ["sdxl", "anime", "character"]
    },
    {
      "name": "Marvel Comics SDXL",
      "description": "Bold lines and cinematic palettes inspired by Marvel comics and films.",
      "repo_id": "smit-mehta/marvel-sdxl",
      "filename": "pytorch_lora_weights.bin",
      "path": "lora/marvel-sdxl/pytorch_lora_weights.bin",
      "preview_url": null,
      "tags": ["sdxl", "comics", "marvel", "superhero"]
    },
    {
      "name": "Comic Legends SDXL",
      "description": "Classic heroic comic aesthetic suited for DC-style characters.",
      "repo_id": "Kousha/comic_person_LoRA",
      "filename": "pytorch_lora_weights.safetensors",
      "path": "lora/comic-legends/pytorch_lora_weights.safetensors",
      "preview_url": null,
      "tags": ["sdxl", "comics", "dc", "superhero"]
    },
    {
      "name": "Final Fantasy Hero SDXL",
      "description": "High-fantasy JRPG styling reminiscent of Final Fantasy concept art.",
      "repo_id": "ntc-ai/SDXL-LoRA-slider.Awesome-Final-Fantasy-character",
      "filename": "Awesome Final Fantasy character.safetensors",
      "path": "lora/final-fantasy/Awesome Final Fantasy character.safetensors",
      "preview_url": "https://huggingface.co/ntc-ai/SDXL-LoRA-slider.Awesome-Final-Fantasy-character/resolve/main/images/Awesome%20Final%20Fantasy%20character_19_0.0.png",
      "tags": ["sdxl", "jrpg", "fantasy", "video game"]
    },
    {
      "name": "Animated Feature SDXL",
      "description": "Soft lighting and expressive faces inspired by modern animated movies.",
      "repo_id": "ZachX/disney_SDXL_lora",
      "filename": "disney_SDXL_lora.safetensors",
      "path": "lora/animated-feature/disney_SDXL_lora.safetensors",
      "preview_url": null,
      "tags": ["sdxl", "disney", "animated", "movie"]
    }
  ]
}
